auto_wrench-0.3.0.dist-info/METADATA
auto_wrench-0.3.0.dist-info/WHEEL
auto_wrench-0.3.0.dist-info/entry_points.txt
auto_wrench-0.3.0.dist-info/licenses/LICENSE
wrench/__init__.py
wrench/cataloger/__init__.py
wrench/cataloger/base.py
wrench/cataloger/sddi/__init__.py
wrench/cataloger/sddi/cataloger.py
wrench/cataloger/sddi/config.py
wrench/cataloger/sddi/models.py
wrench/components/__init__.py
wrench/components/cataloger.py
wrench/components/grouper.py
wrench/components/harvester.py
wrench/components/metadataenricher.py
wrench/components/types.py
wrench/exceptions.py
wrench/grouper/__init__.py
wrench/grouper/base.py
wrench/grouper/bertopic/__init__.py
wrench/grouper/bertopic/bertopic_grouper.py
wrench/grouper/bertopic/models.py
wrench/grouper/kinetic/__init__.py
wrench/grouper/kinetic/_classifier.py
wrench/grouper/kinetic/cooccurence.py
wrench/grouper/kinetic/embedder.py
wrench/grouper/kinetic/keyword_extractor.py
wrench/grouper/kinetic/kinetic.py
wrench/grouper/kinetic/llm_topic_generator.py
wrench/grouper/kinetic/models.py
wrench/grouper/kinetic/prompts/embed_documents.txt
wrench/grouper/kinetic/prompts/embed_topics.txt
wrench/grouper/kinetic/prompts/generate_seed_topics.txt
wrench/grouper/kinetic/prompts/user_prompt.txt
wrench/grouper/kinetic/stopwords/stopwords-de.txt
wrench/grouper/kinetic/stopwords/stopwords-en.txt
wrench/grouper/lda/__init__.py
wrench/grouper/lda/hyperparameter_optimizer.py
wrench/grouper/lda/lda_grouper.py
wrench/grouper/lda/models.py
wrench/grouper/lda/prompts/lda_topic_naming_system.txt
wrench/grouper/lda/prompts/lda_topic_naming_user.txt
wrench/grouper/lda/topic_namer.py
wrench/grouper/teleclass/__init__.py
wrench/grouper/teleclass/classifier/__init__.py
wrench/grouper/teleclass/classifier/similarity.py
wrench/grouper/teleclass/core/__init__.py
wrench/grouper/teleclass/core/cache.py
wrench/grouper/teleclass/core/config.py
wrench/grouper/teleclass/core/document_loader.py
wrench/grouper/teleclass/core/models.py
wrench/grouper/teleclass/core/taxonomy_manager.py
wrench/grouper/teleclass/core/teleclass.py
wrench/grouper/teleclass/enrichment/__init__.py
wrench/grouper/teleclass/enrichment/base.py
auto_wrench-0.3.0.dist-info/RECORD
