Metadata-Version: 2.1
Name: auto-wrench
Version: 0.3.0
Summary: Automated registration package for urban sensor endpoints into metadata catalogs
Author-Email: Jeffrey Limnardy <jeffreylimnardy@yahoo.com>
License: MIT
Requires-Python: <3.13,>=3.12
Requires-Dist: pydantic<3.0.0,>=2.10.4
Requires-Dist: requests<3.0.0,>=2.32.3
Requires-Dist: ckanapi<5.0,>=4.8
Requires-Dist: python-dotenv>=1.0.1
Requires-Dist: geojson>=3.2.0
Requires-Dist: pyyaml>=6.0.0
Requires-Dist: xxhash>=3.5.0
Requires-Dist: apscheduler>=3.11.0
Requires-Dist: openai>=1.76.0
Requires-Dist: matplotlib>=3.10.1
Requires-Dist: psutil>=6.1.0
Provides-Extra: teleclass
Requires-Dist: sentence-transformers>=3.3.1; extra == "teleclass"
Requires-Dist: networkx>=3.4.2; extra == "teleclass"
Requires-Dist: numpy>=2.2.1; extra == "teleclass"
Requires-Dist: ollama>=0.4.5; extra == "teleclass"
Requires-Dist: yake>=0.4.8; extra == "teleclass"
Requires-Dist: rank_bm25>=0.2.2; extra == "teleclass"
Provides-Extra: sensorthings
Requires-Dist: paho-mqtt>=2.1.0; extra == "sensorthings"
Provides-Extra: kinetic
Requires-Dist: flair>=0.15.1; extra == "kinetic"
Requires-Dist: keybert>=0.9.0; extra == "kinetic"
Requires-Dist: networkx>=3.4.2; extra == "kinetic"
Requires-Dist: python-louvain>=0.16; extra == "kinetic"
